echo_report/__innit__.py
echo_report/report_dual_html.py
echo_report/report_html.py
echo_report/visualization.py
echo_report_lab-0.1.2.dist-info/METADATA
echo_report_lab-0.1.2.dist-info/WHEEL
echo_report_lab-0.1.2.dist-info/top_level.txt
echo_report_lab-0.1.2.dist-info/RECORD
