Metadata-Version: 2.4
Name: echo-report-lab
Version: 0.1.2
Summary: Modular Keras report generator — visual embeddings, metrics, model summary, and source archive
Author: Patrick Rutledge
Author-email: Patrick Rutledge <your@email.com>
Requires-Python: >=3.12
Requires-Dist: tensorflow-cpu
Requires-Dist: keras
Requires-Dist: matplotlib
Requires-Dist: scikit-learn
Requires-Dist: numpy
Requires-Dist: pandas
Dynamic: author
Dynamic: requires-python
